wellcode_cli/__init__.py
wellcode_cli/config.py
wellcode_cli/main.py
wellcode_cli/split_metrics.py
wellcode_cli/utils.py
wellcode_cli/commands/__init__.py
wellcode_cli/commands/chat.py
wellcode_cli/commands/chat_interface.py
wellcode_cli/commands/commands.py
wellcode_cli/commands/completion.py
wellcode_cli/commands/config.py
wellcode_cli/commands/report.py
wellcode_cli/commands/review.py
wellcode_cli/github/app_config.py
wellcode_cli/github/auth.py
wellcode_cli/github/client.py
wellcode_cli/github/decorators.py
wellcode_cli/github/github_display.py
wellcode_cli/github/github_format_ai.py
wellcode_cli/github/github_metrics.py
wellcode_cli/github/utils.py
wellcode_cli/github/models/metrics.py
wellcode_cli/linear/linear_display.py
wellcode_cli/linear/linear_metrics.py
wellcode_cli/linear/models/metrics.py
wellcode_cli-0.1.39.dist-info/METADATA
wellcode_cli-0.1.39.dist-info/WHEEL
wellcode_cli-0.1.39.dist-info/entry_points.txt
wellcode_cli-0.1.39.dist-info/licenses/LICENSE
wellcode_cli-0.1.39.dist-info/RECORD
