Metadata-Version: 2.3
Name: wellcode-cli
Version: 0.1.39
Summary: Engineering Metrics Analysis Tool
Project-URL: Homepage, https://github.com/wellcode-ai/wellcode-cli
Project-URL: Repository, https://github.com/wellcode-ai/wellcode-cli
Author-email: Your Name <your.email@example.com>
License:        GNU GENERAL PUBLIC LICENSE
Classifier: License :: OSI Approved :: MIT License
Classifier: Operating System :: OS Independent
Classifier: Programming Language :: Python :: 3
Requires-Python: >=3.8
Requires-Dist: anthropic>=0.18.0
Requires-Dist: certifi>=2023.7.22
Requires-Dist: chardet>=5.2.0
Requires-Dist: click>=8.0.0
Requires-Dist: idna>=3.6
Requires-Dist: pandas>=2.0.0
Requires-Dist: plotly>=5.18.0
Requires-Dist: prompt-toolkit>=3.0.48
Requires-Dist: pygithub>=1.55
Requires-Dist: pyperclip>=1.9.0
Requires-Dist: python-dateutil>=2.8.2
Requires-Dist: python-dotenv>=1.0.0
Requires-Dist: requests>=2.31.0
Requires-Dist: rich-click>=1.6.0
Requires-Dist: rich>=13.0.0
Requires-Dist: splitio-client>=9.2.0
Requires-Dist: urllib3>=2.0.7
Provides-Extra: test
Requires-Dist: pytest-cov>=4.0.0; extra == 'test'
Requires-Dist: pytest>=7.0.0; extra == 'test'
